graphgrid_sdk/__init__.py
graphgrid_sdk/ggcore/__init__.py
graphgrid_sdk/ggcore/api.py
graphgrid_sdk/ggcore/client.py
graphgrid_sdk/ggcore/client_factory.py
graphgrid_sdk/ggcore/config.py
graphgrid_sdk/ggcore/core.py
graphgrid_sdk/ggcore/http_base.py
graphgrid_sdk/ggcore/nmt_train_pipeline.py
graphgrid_sdk/ggcore/sdk_exceptions.py
graphgrid_sdk/ggcore/sdk_messages.py
graphgrid_sdk/ggcore/security_base.py
graphgrid_sdk/ggcore/session.py
graphgrid_sdk/ggcore/utils.py
graphgrid_sdk/ggsdk/__init__.py
graphgrid_sdk/ggsdk/bootstrap.py
graphgrid_sdk/ggsdk/sdk.py
graphgrid_sdk-2.0.1.dist-info/METADATA
graphgrid_sdk-2.0.1.dist-info/WHEEL
graphgrid_sdk-2.0.1.dist-info/top_level.txt
graphgrid_sdk-2.0.1.dist-info/RECORD
