Metadata-Version: 2.1
Name: graphgrid-sdk
Version: 2.0.1
Summary: GraphGrid Python SDK
Home-page: https://docs.graphgrid.com/2.0/#/
Author: graphgrid
Author-email: 
Classifier: Development Status :: 5 - Production/Stable
Classifier: Programming Language :: Python :: 3.6
Classifier: Programming Language :: Python :: 3.7
Classifier: Programming Language :: Python :: 3.8
Requires-Python: !=3.9.*, >=3.6
Requires-Dist: requests (~=2.27.1)
Requires-Dist: javaproperties (~=0.8.1)
